odoo/addons/product_old_migration_fields/README.rst
odoo/addons/product_old_migration_fields/__init__.py
odoo/addons/product_old_migration_fields/__manifest__.py
odoo/addons/product_old_migration_fields/i18n/es.po
odoo/addons/product_old_migration_fields/models/__init__.py
odoo/addons/product_old_migration_fields/models/product.py
odoo/addons/product_old_migration_fields/models/product_category.py
odoo/addons/product_old_migration_fields/static/description/icon.png
odoo/addons/product_old_migration_fields/views/product_category_views.xml
odoo/addons/product_old_migration_fields/views/product_views.xml
odoo_addon_product_old_migration_fields-17.0.1.0.1.1.dist-info/METADATA
odoo_addon_product_old_migration_fields-17.0.1.0.1.1.dist-info/WHEEL
odoo_addon_product_old_migration_fields-17.0.1.0.1.1.dist-info/top_level.txt
odoo_addon_product_old_migration_fields-17.0.1.0.1.1.dist-info/RECORD
